blofin_api/__init__.py
blofin_api-0.0.1.dist-info/METADATA
blofin_api-0.0.1.dist-info/WHEEL
blofin_api-0.0.1.dist-info/top_level.txt
blofin_api-0.0.1.dist-info/RECORD
