Metadata-Version: 2.1
Name: blofin_api
Version: 0.0.1
Summary: BloFin API SDK
Author-email: Nomeida <nomeida@proton.me>
License: MIT
Classifier: Programming Language :: Python :: 3
